memgpt/__init__.py
memgpt/__main__.py
memgpt/agent.py
memgpt/autogen/README.md
memgpt/autogen/__init__.py
memgpt/autogen/examples/agent_autoreply.py
memgpt/autogen/examples/agent_docs.py
memgpt/autogen/examples/agent_groupchat.py
memgpt/autogen/examples/memgpt_coder_autogen.ipynb
memgpt/autogen/interface.py
memgpt/autogen/memgpt_agent.py
memgpt/cli/cli.py
memgpt/cli/cli_config.py
memgpt/cli/cli_load.py
memgpt/config.py
memgpt/connectors/db.py
memgpt/connectors/local.py
memgpt/connectors/storage.py
memgpt/constants.py
memgpt/embeddings.py
memgpt/errors.py
memgpt/functions/__init__.py
memgpt/functions/function_sets/base.py
memgpt/functions/function_sets/extras.py
memgpt/functions/functions.py
memgpt/functions/schema_generator.py
memgpt/humans/__init__.py
memgpt/humans/examples/basic.txt
memgpt/humans/examples/cs_phd.txt
memgpt/humans/humans.py
memgpt/interface.py
memgpt/local_llm/README.md
memgpt/local_llm/__init__.py
memgpt/local_llm/chat_completion_proxy.py
memgpt/local_llm/constants.py
memgpt/local_llm/grammars/json.gbnf
memgpt/local_llm/grammars/json_func_calls_with_inner_thoughts.gbnf
memgpt/local_llm/json_parser.py
memgpt/local_llm/koboldcpp/api.py
memgpt/local_llm/koboldcpp/settings.py
memgpt/local_llm/llamacpp/api.py
memgpt/local_llm/llamacpp/settings.py
memgpt/local_llm/llm_chat_completion_wrappers/__init__.py
memgpt/local_llm/llm_chat_completion_wrappers/airoboros.py
memgpt/local_llm/llm_chat_completion_wrappers/dolphin.py
memgpt/local_llm/llm_chat_completion_wrappers/simple_summary_wrapper.py
memgpt/local_llm/llm_chat_completion_wrappers/wrapper_base.py
memgpt/local_llm/llm_chat_completion_wrappers/zephyr.py
memgpt/local_llm/lmstudio/api.py
memgpt/local_llm/lmstudio/settings.py
memgpt/local_llm/ollama/api.py
memgpt/local_llm/ollama/settings.py
memgpt/local_llm/utils.py
memgpt/local_llm/vllm/api.py
memgpt/local_llm/webui/api.py
memgpt/local_llm/webui/legacy_api.py
memgpt/local_llm/webui/legacy_settings.py
memgpt/local_llm/webui/settings.py
memgpt/main.py
pymemgpt_setdir-0.2.4.dist-info/LICENSE
pymemgpt_setdir-0.2.4.dist-info/METADATA
pymemgpt_setdir-0.2.4.dist-info/WHEEL
pymemgpt_setdir-0.2.4.dist-info/entry_points.txt
pymemgpt_setdir-0.2.4.dist-info/RECORD
