Metadata-Version: 2.1
Name: pymemgpt_setdir
Version: 0.2.4
Summary: Teaching LLMs memory management for unbounded context
License: Apache License
Author: Charles Packer
Author-email: contact@charlespacker.com
Requires-Python: >=3.9,<3.12
Classifier: License :: Other/Proprietary License
Classifier: Programming Language :: Python :: 3
Classifier: Programming Language :: Python :: 3.9
Classifier: Programming Language :: Python :: 3.10
Classifier: Programming Language :: Python :: 3.11
Provides-Extra: dev
Provides-Extra: lancedb
Provides-Extra: legacy
Provides-Extra: local
Provides-Extra: postgres
Requires-Dist: black (>=23.10.1,<24.0.0) ; extra == "dev"
Requires-Dist: datasets (>=2.14.6,<3.0.0) ; extra == "dev"
Requires-Dist: demjson3 (>=3.0.6,<4.0.0)
Requires-Dist: docstring-parser (>=0.15,<0.16)
Requires-Dist: faiss-cpu (>=1.7.4,<2.0.0) ; extra == "legacy"
Requires-Dist: huggingface-hub (==0.17.3) ; extra == "local"
Requires-Dist: lancedb (>=0.3.3,<0.4.0) ; extra == "lancedb"
Requires-Dist: llama-index (>=0.8.53.post3,<0.9.0)
Requires-Dist: numpy (>=1.26.1,<2.0.0) ; extra == "legacy"
Requires-Dist: openai (>=0.28.1,<0.29.0)
Requires-Dist: pg8000 (>=1.30.3,<2.0.0) ; extra == "postgres"
Requires-Dist: pgvector (>=0.2.3,<0.3.0) ; extra == "postgres"
Requires-Dist: pre-commit (>=3.5.0,<4.0.0) ; extra == "dev"
Requires-Dist: prettytable (>=3.9.0,<4.0.0)
Requires-Dist: psycopg (>=3.1.12,<4.0.0) ; extra == "postgres"
Requires-Dist: psycopg-binary (>=3.1.12,<4.0.0) ; extra == "postgres"
Requires-Dist: psycopg2-binary (>=2.9.9,<3.0.0) ; extra == "postgres"
Requires-Dist: pymupdf (>=1.23.5,<2.0.0)
Requires-Dist: pytest (>=7.4.3,<8.0.0) ; extra == "dev"
Requires-Dist: pytz (>=2023.3.post1,<2024.0)
Requires-Dist: questionary (>=2.0.1,<3.0.0)
Requires-Dist: setuptools (>=68.2.2,<69.0.0)
Requires-Dist: tiktoken (>=0.5.1,<0.6.0)
Requires-Dist: torch (>=2.0.0,!=2.0.1,!=2.1.0) ; extra == "local"
Requires-Dist: tqdm (>=4.66.1,<5.0.0)
Requires-Dist: transformers (==4.34.1) ; extra == "local"
Requires-Dist: typer[all] (>=0.9.0,<0.10.0)
Requires-Dist: websockets (>=12.0,<13.0)
